[
  {
    "id": "trash-to-treasure-upcycling",
    "name": "From Trash to Treasure: The Ultimate Guide to Creative Upcycling",
    "vendor": "UPNEST",
    "category": "Home & Garden",
    "niche": "crafts / sustainable DIY home decor",
    "price": "low-ticket (official page)",
    "summary": "A step-by-step guide teaching sustainable DIY projects that transform everyday waste into beautiful home decor.",
    "best_for": "Budget-conscious DIYers and eco-minded crafters who want to repurpose household items into decor pieces.",
    "keywords": [
      "trash to treasure upcycling review",
      "upcycling DIY guide",
      "sustainable home decor projects",
      "creative upcycling ideas book"
    ],
    "clickbank_stats": {
      "gravity": 0.0,
      "approval_required": false
    }
  },
  {
    "id": "davids-shield-emp-guide",
    "name": "David's Shield",
    "vendor": "BOUSA1",
    "category": "Self-Help",
    "niche": "survival / preparedness",
    "price": "low-ticket (official page)",
    "summary": "A preparedness guide focused on protecting household electronics and essentials from EMP-related power disruptions.",
    "best_for": "Preparedness-minded homeowners who want practical steps to safeguard electronics and daily essentials during power disruptions.",
    "keywords": [
      "david's shield review",
      "emp preparedness guide",
      "protect electronics power outage",
      "survival prepper guide"
    ],
    "clickbank_stats": {
      "gravity": 24.7,
      "approval_required": false
    }
  },
  {
    "id": "the-lost-superfoods",
    "name": "The Lost SuperFoods",
    "vendor": "LOSTREC",
    "category": "Self-Help",
    "niche": "survival / preparedness food storage",
    "price": "low-ticket (official page)",
    "summary": "A guide from the creators of The Lost Ways covering forgotten superfoods and long-term food storage methods for self-sufficiency.",
    "best_for": "Preppers and self-sufficiency enthusiasts who want to build a long-lasting, nutrient-dense food stockpile.",
    "keywords": [
      "the lost superfoods review",
      "long term food storage guide",
      "prepper food stockpile",
      "survival superfoods book"
    ],
    "clickbank_stats": {
      "gravity": 10.3,
      "approval_required": false
    }
  }
]